yt_fetcher/__init__.py
yt_fetcher/cli.py
yt_fetcher_new-0.2.dist-info/licenses/LICENSE
yt_fetcher_new-0.2.dist-info/METADATA
yt_fetcher_new-0.2.dist-info/WHEEL
yt_fetcher_new-0.2.dist-info/entry_points.txt
yt_fetcher_new-0.2.dist-info/top_level.txt
yt_fetcher_new-0.2.dist-info/RECORD
